{
  "type": "minecraft:command",
  "pools": [
    {
      "rolls": 1,
      "entries": [
        {
          "type": "minecraft:item",
          "name": "minecraft:firework_rocket",
          "functions": [
            {
              "function": "minecraft:set_nbt",
              "tag": "{CanDestroy:[\"#game:useable\"],HideFlags:10,drop:1b}"
            },
            {
              "function": "minecraft:set_attributes",
              "modifiers": [
                {
                  "attribute": "minecraft:generic.luck",
                  "name": "unstackable",
                  "amount": 0,
                  "operation": "addition",
                  "slot": "head"
                }
              ]
            }
          ]
        }
      ]
    }
  ]
}
